bin/ssm-dev-start
bin/ssm-dev-stop
bin/ssm-setup
shadowsocks_manager/__init__.py
shadowsocks_manager/__main__.py
shadowsocks_manager/manage.py
shadowsocks_manager/args_formatter/__init__.py
shadowsocks_manager/args_formatter/tests.py
shadowsocks_manager/domain/__init__.py
shadowsocks_manager/domain/admin.py
shadowsocks_manager/domain/apps.py
shadowsocks_manager/domain/models.py
shadowsocks_manager/domain/serializers.py
shadowsocks_manager/domain/tests.py
shadowsocks_manager/domain/urls.py
shadowsocks_manager/domain/views.py
shadowsocks_manager/domain/management/__init__.py
shadowsocks_manager/domain/management/commands/__init__.py
shadowsocks_manager/domain/management/commands/domain_domain.py
shadowsocks_manager/domain/management/commands/domain_nameserver.py
shadowsocks_manager/domain/management/commands/domain_record.py
shadowsocks_manager/domain/management/commands/domain_site.py
shadowsocks_manager/domain/migrations/__init__.py
shadowsocks_manager/dynamicmethod/__init__.py
shadowsocks_manager/dynamicmethod/admin.py
shadowsocks_manager/dynamicmethod/apps.py
shadowsocks_manager/dynamicmethod/models.py
shadowsocks_manager/dynamicmethod/tests.py
shadowsocks_manager/dynamicmethod/migrations/__init__.py
shadowsocks_manager/fixture/__init__.py
shadowsocks_manager/fixture/fixtures/auth.group.json
shadowsocks_manager/fixture/fixtures/django_celery_beat.crontabschedule.json
shadowsocks_manager/fixture/fixtures/django_celery_beat.intervalschedule.json
shadowsocks_manager/fixture/fixtures/django_celery_beat.periodictask.json
shadowsocks_manager/fixture/fixtures/sites.site.json
shadowsocks_manager/notification/__init__.py
shadowsocks_manager/notification/admin.py
shadowsocks_manager/notification/apps.py
shadowsocks_manager/notification/models.py
shadowsocks_manager/notification/serializers.py
shadowsocks_manager/notification/tests.py
shadowsocks_manager/notification/urls.py
shadowsocks_manager/notification/views.py
shadowsocks_manager-0.1.17.dist-info/LICENSE
shadowsocks_manager-0.1.17.dist-info/METADATA
shadowsocks_manager-0.1.17.dist-info/WHEEL
shadowsocks_manager-0.1.17.dist-info/entry_points.txt
shadowsocks_manager-0.1.17.dist-info/top_level.txt
shadowsocks_manager-0.1.17.dist-info/RECORD
