Metadata-Version: 2.1
Name: shadowsocks-manager
Version: 0.1.17
Summary: A shadowsocks manager for multi-user and traffic statistics
Home-page: https://github.com/alexzhangs/shadowsocks-manager
Author: Alex
Author-email: Alex <alexzhangs@gmail.com>
License: MIT License
Project-URL: homepage, https://www.0xbeta.com/shadowsocks-manager/
Project-URL: repository, https://github.com/alexzhangs/shadowsocks-manager
Project-URL: issues, https://github.com/alexzhangs/shadowsocks-manager/issues
Keywords: shadowsocks,manager,django,web,statistics,cluster,celery,uwsgi,pypi,docker,github-actions
Classifier: Development Status :: 4 - Beta
Classifier: Environment :: Web Environment
Classifier: Framework :: Django
Classifier: Intended Audience :: Developers
Classifier: License :: OSI Approved :: MIT License
Classifier: Operating System :: MacOS
Classifier: Operating System :: POSIX :: Linux
Classifier: Programming Language :: Python
Classifier: Programming Language :: Python :: 2
Classifier: Programming Language :: Python :: 2.7
Classifier: Programming Language :: Python :: 3
Classifier: Programming Language :: Python :: 3.7
Classifier: Programming Language :: Python :: 3.8
Classifier: Programming Language :: Python :: 3.9
Classifier: Programming Language :: Python :: 3.10
Classifier: Programming Language :: Python :: 3.11
Classifier: Programming Language :: Python :: 3.12
Classifier: Topic :: Internet :: Proxy Servers
Classifier: Topic :: Internet :: WWW/HTTP
Classifier: Topic :: Internet :: WWW/HTTP :: WSGI :: Application
Classifier: Topic :: Security :: Cryptography
Classifier: Topic :: System :: Networking :: Firewalls
Requires-Python: >=2.7
License-File: LICENSE
Requires-Dist: future
Requires-Dist: six
Requires-Dist: boto3
Requires-Dist: celery
Requires-Dist: Django <4
Requires-Dist: django-admin-lazy-load-alexforks
Requires-Dist: django-allowedsites-dynamic
Requires-Dist: django-cache-lock
Requires-Dist: django-import-export <=3.3.9
Requires-Dist: djangorestframework
Requires-Dist: dns-lexicon[full]
Requires-Dist: dnspython
Requires-Dist: docopt
Requires-Dist: psutil
Requires-Dist: python-decouple
Requires-Dist: python-memcached ==1.59
Requires-Dist: pytz
Requires-Dist: requests
Requires-Dist: tldextract
Requires-Dist: uWSGI
Requires-Dist: ipaddress ; python_version < "3.3"
Requires-Dist: django-admin-easy ==0.4.1 ; python_version <= "2.7"
Requires-Dist: django-celery-beat ==1.6.0 ; python_version <= "2.7"
Requires-Dist: django-celery-results ==2.0.1 ; python_version <= "2.7"
Requires-Dist: django-enumfield <3.0 ; python_version <= "2.7"
Requires-Dist: django-filter ~=1.1 ; python_version <= "2.7"
Requires-Dist: python-crontab ==2.6.0 ; python_version <= "2.7"
Requires-Dist: Softlayer ==5.8.0 ; python_version <= "2.7"
Requires-Dist: django-admin-easy ; python_version > "2.7"
Requires-Dist: django-celery-results ; python_version > "2.7"
Requires-Dist: django-enumfield ; python_version > "2.7"
Requires-Dist: django-filter ; python_version > "2.7"
Requires-Dist: python-crontab ; python_version > "2.7"
Requires-Dist: Softlayer ; python_version > "2.7"
Requires-Dist: django-celery-beat <2.6.0 ; python_version > "2.7" and python_version < "3.8"
Requires-Dist: django-celery-beat ; python_version >= "3.8"
Provides-Extra: release
Requires-Dist: codecov ; extra == 'release'
Requires-Dist: build ; extra == 'release'
Requires-Dist: bump-my-version ; extra == 'release'
Requires-Dist: setuptools ; extra == 'release'
Requires-Dist: twine ; extra == 'release'
Requires-Dist: wheel ; extra == 'release'
Provides-Extra: test
Requires-Dist: mock ; (python_version <= "2.7") and extra == 'test'
Requires-Dist: coverage[toml] ; (python_version >= "2.7" and python_version < "3.11") and extra == 'test'
Requires-Dist: coverage ; (python_version >= "3.11") and extra == 'test'
